checker/BakuChecker.py
checker/BaseChecker.py
checker/__init__.py
checker/check.py
checker/improveDict.py
kata_baku_checkr_po_file-0.1.2.dist-info/LICENSE
kata_baku_checkr_po_file-0.1.2.dist-info/METADATA
kata_baku_checkr_po_file-0.1.2.dist-info/WHEEL
kata_baku_checkr_po_file-0.1.2.dist-info/top_level.txt
kata_baku_checkr_po_file-0.1.2.dist-info/RECORD
