Metadata-Version: 2.1
Name: kata-baku-checkr-po-file
Version: 0.1.2
Summary: Checker for Kata Baku for PO File reader
Home-page: https://github.com/bervProject/Kata-Baku-Checker-for-PO-File/
Author: Bervianto Leo Pratama
Author-email: bervianto.leo@gmail.com
License: UNKNOWN
Platform: UNKNOWN
Classifier: Programming Language :: Python :: 3
Classifier: License :: OSI Approved :: MIT License
Classifier: Operating System :: OS Independent
Requires-Python: >=3.6
Requires-Dist: polib
